{
  "authKey": "1307b1368845c0a4caac2e8412f24902",
  "agentId": "agent_main_1758974357",
  "startTime": "2025-09-27T12:00:57.705Z",
  "expiresAt": "2025-09-27T12:30:57.705Z",
  "currentStep": 6,
  "completedSteps": [
    "focused-codebase",
    "security-validation",
    "linter-validation",
    "type-validation",
    "build-validation",
    "start-validation"
  ],
  "requiredSteps": [
    "focused-codebase",
    "security-validation",
    "linter-validation",
    "type-validation",
    "build-validation",
    "start-validation",
    "test-validation"
  ],
  "status": "in_progress",
  "lastValidation": "2025-09-27T12:01:35.279Z"
}